LICENSE
MANIFEST.in
README.rst
gp-mode.json
setup.py
PARIKernel/__init__.py
PARIKernel/__main__.py
PARIKernel/io.c
PARIKernel/io.pxd
PARIKernel/io.pyx
PARIKernel/kernel.c
PARIKernel/kernel.pyx
PARIKernel/paridecl.pxd
PARIKernel/svg.c
PARIKernel/svg.pyx
gp-mode/gp.js
gp-mode/main.js
pari_jupyter.egg-info/PKG-INFO
pari_jupyter.egg-info/SOURCES.txt
pari_jupyter.egg-info/dependency_links.txt
pari_jupyter.egg-info/requires.txt
pari_jupyter.egg-info/top_level.txt
spec/kernel.js
spec/kernel.json
spec/logo-64x64.png
test/test_pari_jupyter_kernel.py