Metadata-Version: 2.1
Name: pari-jupyter
Version: 1.4.2
Summary: A Jupyter kernel for PARI/GP
Home-page: https://github.com/sagemath/pari-jupyter
Author: Jeroen Demeyer
Author-email: pari-users@pari.math.u-bordeaux.fr
License: GNU General Public License (GPL) version 3 or later
Platform: POSIX
Classifier: Development Status :: 5 - Production/Stable
Classifier: License :: OSI Approved :: GNU General Public License v3 or later (GPLv3+)
Classifier: Operating System :: POSIX
Classifier: Programming Language :: Cython
Classifier: Intended Audience :: Science/Research
Classifier: Topic :: Scientific/Engineering :: Mathematics
License-File: LICENSE
